Workbook

Sheet Assumptions
A1: Category | B1: Variable Name | C1: Value | D1: Unit
A2: CapEx | B2: Implementation Consulting Fee | C2: 50000 | D2: $
A3: CapEx | B3: Initial Training Time Per User | C3: 5 | D3: Hours
A4: OpEx | B4: Monthly AI License Fee | C4: 30 | D4: $/user/month
A5: OpEx | B5: Total number of Users | C5: 200 | D5: Employees
A6: Benefits | B6: Average Employee Salary | C6: 85000 | D6: $/year
A7: Benefits | B7: Time Saved per Week | C7: 8 | D7: Hours

Sheet Cost_Tableau Export
A1: Line Item | B1: Month | C1: Amount
A2: Implementation Fee | B2: 0 | C2: 50000
A3: Implementation Fee | B3: 1 | C3: 0
A4: Implementation Fee | B4: 2 | C4: 0
A5: Implementation Fee | B5: 3 | C5: 0
A6: Implementation Fee | B6: 4 | C6: 0
A7: Implementation Fee | B7: 5 | C7: 0
A8: Implementation Fee | B8: 6 | C8: 0
A9: Implementation Fee | B9: 7 | C9: 0
A10: Implementation Fee | B10: 8 | C10: 0
A11: Implementation Fee | B11: 9 | C11: 0
A12: Implementation Fee | B12: 10 | C12: 0
A13: Implementation Fee | B13: 11 | C13: 0
... A149: TOTAL MONTHLY COSTS | B149: 36 | C149: 6000

Sheet Costs
A1: Month | B1: 0 | C1: 1 | D1: 2 | E1: 3 | F1: 4 | G1: 5 | H1: 6 | I1: 7 | J1: 8 | K1: 9 | L1: 10 | M1: 11 | N1: 12 | O1: 13 | P1: 14 | Q1: 15 | R1: 16 | S1: 17 | T1: 18 | U1: 19 | V1: 20 | W1: 21 | X1: 22 | Y1: 23 | Z1: 24 | AA1: 25 | AB1: 26 | AC1: 27 | AD1: 28 | AE1: 29 | AF1: 30 | AG1: 31 | AH1: 32 | AI1: 33 | AJ1: 34 | AK1: 35 | AL1: 36
A2: Implementation Fee | B2: =Assumptions!C2 -> 50000 | C2: 0 | D2: 0 | E2: 0 | F2: 0 | G2: 0 | H2: 0 | I2: 0 | J2: 0 | K2: 0 | L2: 0 | M2: 0 | N2: 0 | O2: 0 | P2: 0 | Q2: 0 | R2: 0 | S2: 0 | T2: 0 | U2: 0 | V2: 0 | W2: 0 | X2: 0 | Y2: 0 | Z2: 0 | AA2: 0 | AB2: 0 | AC2: 0 | AD2: 0 | AE2: 0 | AF2: 0 | AG2: 0 | AH2: 0 | AI2: 0 | AJ2: 0 | AK2: 0 | AL2: 0
A3: Initial Training Cost | B3: =(Assumptions!C3*Assumptions!C5)*(Assumptions!C6/2000) -> 42500 | C3: 0 | D3: 0 | E3: 0 | F3: 0 | G3: 0 | H3: 0 | I3: 0 | J3: 0 | K3: 0 | L3: 0 | M3: 0 | N3: 0 | O3: 0 | P3: 0 | Q3: 0 | R3: 0 | S3: 0 | T3: 0 | U3: 0 | V3: 0 | W3: 0 | X3: 0 | Y3: 0 | Z3: 0 | AA3: 0 | AB3: 0 | AC3: 0 | AD3: 0 | AE3: 0 | AF3: 0 | AG3: 0 | AH3: 0 | AI3: 0 | AJ3: 0 | AK3: 0 | AL3: 0
A4: Monthly AI Licenses | B4: 0 | C4: =Assumptions!$C$4 * Assumptions!$C$5 -> 6000 | D4: =Assumptions!$C$4 * Assumptions!$C$5 -> 6000 | E4: =Assumptions!$C$4 * Assumptions!$C$5 -> 6000 | F4: =Assumptions!$C$4 * Assumptions!$C$5 -> 6000 | G4: =Assumptions!$C$4 * Assumptions!$C$5 -> 6000 | H4: =Assumptions!$C$4 * Assumptions!$C$5 -> 6000 | I4: =Assumptions!$C$4 * Assumptions!$C$5 -> 6000 | J4: =Assumptions!$C$4 * Assumptions!$C$5 -> 6000 | ... AL4: =Assumptions!$C$4 * Assumptions!$C$5 -> 6000
A6: TOTAL MONTHLY COSTS | B6: =SUM(B2:B4) -> 92500 | C6: =SUM(C2:C4) -> 6000 | D6: =SUM(D2:D4) -> 6000 | E6: =SUM(E2:E4) -> 6000 | F6: =SUM(F2:F4) -> 6000 | G6: =SUM(G2:G4) -> 6000 | H6: =SUM(H2:H4) -> 6000 | I6: =SUM(I2:I4) -> 6000 | ... AL6: =SUM(AL2:AL4) -> 6000

Sheet Benefits_Tableau Export
A1: Line Item | B1: Month | C1: Amount
A2: Adoption Rate | B2: 0 | C2: 0
A3: Adoption Rate | B3: 1 | C3: 0.1
A4: Adoption Rate | B4: 2 | C4: 0.25
A5: Adoption Rate | B5: 3 | C5: 0.5
A6: Adoption Rate | B6: 4 | C6: 0.75
A7: Adoption Rate | B7: 5 | C7: 0.9
A8: Adoption Rate | B8: 6 | C8: 1
A9: Adoption Rate | B9: 7 | C9: 1
A10: Adoption Rate | B10: 8 | C10: 1
A11: Adoption Rate | B11: 9 | C11: 1
A12: Adoption Rate | B12: 10 | C12: 1
A13: Adoption Rate | B13: 11 | C13: 1
... A186: TOTAL MONTHLY BENEFITS | B186: 36 | C186: 283115.38

Sheet Benefits
A1: Month | B1: =Costs!B1 -> 0 | C1: =Costs!C1 -> 1 | D1: =Costs!D1 -> 2 | E1: =Costs!E1 -> 3 | F1: =Costs!F1 -> 4 | G1: =Costs!G1 -> 5 | H1: =Costs!H1 -> 6 | I1: =Costs!I1 -> 7 | ... AL1: =Costs!AL1 -> 36
A2: Adoption Rate | B2: 0 | C2: 0.1 | D2: 0.25 | E2: 0.5 | F2: 0.75 | G2: 0.9 | H2: 1 | I2: 1 | J2: 1 | K2: 1 | L2: 1 | M2: 1 | N2: 1 | O2: 1 | P2: 1 | Q2: 1 | R2: 1 | S2: 1 | T2: 1 | U2: 1 | V2: 1 | W2: 1 | X2: 1 | Y2: 1 | Z2: 1 | AA2: 1 | AB2: 1 | AC2: 1 | AD2: 1 | AE2: 1 | AF2: 1 | AG2: 1 | AH2: 1 | AI2: 1 | AJ2: 1 | AK2: 1 | AL2: 1
A3: Active AI Users | B3: 0 | C3: =Assumptions!$C$5 * C2 -> 20 | D3: =Assumptions!$C$5 * D2 -> 50 | E3: =Assumptions!$C$5 * E2 -> 100 | F3: =Assumptions!$C$5 * F2 -> 150 | G3: =Assumptions!$C$5 * G2 -> 180 | H3: =Assumptions!$C$5 * H2 -> 200 | I3: =Assumptions!$C$5 * I2 -> 200 | J3: =Assumptions!$C$5 * J2 -> 200 | ... AL3: =Assumptions!$C$5 * AL2 -> 200
A4: Total Hours Saved | B4: 0 | C4: =C3*Assumptions!$C$7 * 4.33 -> 692.8 | D4: =D3*Assumptions!$C$7 * 4.33 -> 1732 | E4: =E3*Assumptions!$C$7 * 4.33 -> 3464 | F4: =F3*Assumptions!$C$7 * 4.33 -> 5196 | G4: =G3*Assumptions!$C$7 * 4.33 -> 6235.2 | H4: =H3*Assumptions!$C$7 * 4.33 -> 6928 | I4: =I3*Assumptions!$C$7 * 4.33 -> 6928 | J4: =J3*Assumptions!$C$7 * 4.33 -> 6928 | ... AL4: =AL3*Assumptions!$C$7 * 4.33 -> 6928
A5: Financial Value of Time Saved | B5: 0 | C5: =C4 * (Assumptions!$C$6 / 2080) -> 28311.538 | D5: =D4 * (Assumptions!$C$6 / 2080) -> 70778.846 | E5: =E4 * (Assumptions!$C$6 / 2080) -> 141557.69 | F5: =F4 * (Assumptions!$C$6 / 2080) -> 212336.54 | G5: =G4 * (Assumptions!$C$6 / 2080) -> 254803.85 | H5: =H4 * (Assumptions!$C$6 / 2080) -> 283115.38 | I5: =I4 * (Assumptions!$C$6 / 2080) -> 283115.38 | J5: =J4 * (Assumptions!$C$6 / 2080) -> 283115.38 | ... AL5: =AL4 * (Assumptions!$C$6 / 2080) -> 283115.38
A7: TOTAL MONTHLY BENEFITS | B7: =SUM(B5) -> 0 | C7: =SUM(C5) -> 28311.538 | D7: =SUM(D5) -> 70778.846 | E7: =SUM(E5) -> 141557.69 | F7: =SUM(F5) -> 212336.54 | G7: =SUM(G5) -> 254803.85 | H7: =SUM(H5) -> 283115.38 | I7: =SUM(I5) -> 283115.38 | ... AL7: =SUM(AL5) -> 283115.38

Sheet Dashboard
A2: Total 3 -Year Investment | B2: =SUM(B11:AL11) -> 308500
A3: Total 3 - Year Savings | B3: =SUM(B12:AL12) -> 9484365.4
A4: Net ROI | B4: =B3-B2 -> 9175865.4
A5: Breakeven Month | B5: 3
A10: Month | B10: =Costs!B1 -> 0 | C10: =Costs!C1 -> 1 | D10: =Costs!D1 -> 2 | E10: =Costs!E1 -> 3 | F10: =Costs!F1 -> 4 | G10: =Costs!G1 -> 5 | H10: =Costs!H1 -> 6 | I10: =Costs!I1 -> 7 | ... AL10: =Costs!AL1 -> 36
A11: Total Costs | B11: =Costs!B6 -> 92500 | C11: =Costs!C6 -> 6000 | D11: =Costs!D6 -> 6000 | E11: =Costs!E6 -> 6000 | F11: =Costs!F6 -> 6000 | G11: =Costs!G6 -> 6000 | H11: =Costs!H6 -> 6000 | I11: =Costs!I6 -> 6000 | ... AL11: =Costs!AL6 -> 6000
A12: Total Benefits | B12: =Benefits!B7 -> 0 | C12: =Benefits!C7 -> 28311.538 | D12: =Benefits!D7 -> 70778.846 | E12: =Benefits!E7 -> 141557.69 | F12: =Benefits!F7 -> 212336.54 | G12: =Benefits!G7 -> 254803.85 | H12: =Benefits!H7 -> 283115.38 | I12: =Benefits!I7 -> 283115.38 | ... AL12: =Benefits!AL7 -> 283115.38
A13: Net Cash Flow | B13: =B12-B11 -> -92500 | C13: =C12-C11 -> 22311.538 | D13: =D12-D11 -> 64778.846 | E13: =E12-E11 -> 135557.69 | F13: =F12-F11 -> 206336.54 | G13: =G12-G11 -> 248803.85 | H13: =H12-H11 -> 277115.38 | I13: =I12-I11 -> 277115.38 | ... AL13: =AL12-AL11 -> 277115.38
A14: Cumulative Cash Flow | B14: =B13 -> -92500 | C14: =B14+C13 -> -70188.462 | D14: =C14+D13 -> -5409.6154 | E14: =D14+E13 -> 130148.08 | F14: =E14+F13 -> 336484.62 | G14: =F14+G13 -> 585288.46 | H14: =G14+H13 -> 862403.85 | I14: =H14+I13 -> 1139519.2 | J14: =I14+J13 -> 1416634.6 | ... AL14: =AK14+AL13 -> 9175865.4

Sheet Tableau Export
A1: Category | B1: Line Item | C1: Month | D1: Amount
A2: Cost | B2: Implementation Fee | C2: 0 | D2: 50000
A3: Cost | B3: Implementation Fee | C3: 1 | D3: 0
A4: Cost | B4: Implementation Fee | C4: 2 | D4: 0
A5: Cost | B5: Implementation Fee | C5: 3 | D5: 0
A6: Cost | B6: Implementation Fee | C6: 4 | D6: 0
A7: Cost | B7: Implementation Fee | C7: 5 | D7: 0
A8: Cost | B8: Implementation Fee | C8: 6 | D8: 0
A9: Cost | B9: Implementation Fee | C9: 7 | D9: 0
A10: Cost | B10: Implementation Fee | C10: 8 | D10: 0
A11: Cost | B11: Implementation Fee | C11: 9 | D11: 0
A12: Cost | B12: Implementation Fee | C12: 10 | D12: 0
A13: Cost | B13: Implementation Fee | C13: 11 | D13: 0
... A334: Benefits | B334: TOTAL MONTHLY BENEFITS | C334: 36 | D334: 283115.38
